jeeves_yeti_pyproject/__init__.py
jeeves_yeti_pyproject/diff.py
jeeves_yeti_pyproject/errors.py
jeeves_yeti_pyproject/files_and_directories.py
jeeves_yeti_pyproject/flags.py
jeeves_yeti_pyproject/jeeves.py
jeeves_yeti_pyproject/mypy.py
jeeves_yeti_pyproject/notifications.py
jeeves_yeti_pyproject-1.0.3.dist-info/METADATA
jeeves_yeti_pyproject-1.0.3.dist-info/WHEEL
jeeves_yeti_pyproject-1.0.3.dist-info/entry_points.txt
jeeves_yeti_pyproject-1.0.3.dist-info/RECORD
