Metadata-Version: 2.4
Name: jeeves-yeti-pyproject
Version: 1.0.3
Summary: Opinionated Jeeves plugin for Python projects.
Author: Anatoly Scherbakov
Author-email: altaisoft@gmail.com
Requires-Python: >=3.10,<4.0
Classifier: Programming Language :: Python :: 3
Classifier: Programming Language :: Python :: 3.10
Classifier: Programming Language :: Python :: 3.11
Classifier: Programming Language :: Python :: 3.12
Classifier: Programming Language :: Python :: 3.13
Classifier: Programming Language :: Python :: 3.14
Requires-Dist: jeeves-shell[all] (>=2.3.0)
Requires-Dist: mkdocs (>=1.4.2)
Requires-Dist: mkdocs-macros-plugin (>=0.7.0)
Requires-Dist: mkdocs-material (>=9.0.3)
Requires-Dist: mypy (<2.0)
Requires-Dist: packaging (>=25.0)
Requires-Dist: pydantic (>=2.9.2,<3.0.0)
Requires-Dist: pytest (>=7.4.2)
Requires-Dist: pytest-cov (>=4.1.0)
Requires-Dist: pytest-randomly (>=3.8)
Requires-Dist: rich (>=13.3.1)
Requires-Dist: ruff (>=0.3.0)
Requires-Dist: safety (>=1.10)
Requires-Dist: tomlkit (>=0.11.6)
Requires-Dist: wemake-python-styleguide (>=1.0.0)
Requires-Dist: yarl (>=1.17.0,<2.0.0)
